doc/error_msg.png
doc/usage_demo.png
xlfly/__init__.py
xlfly/__main__.py
xlfly/about.png
xlfly/about.py
xlfly/addin.py
xlfly/app.py
xlfly/check_package.py
xlfly/configs.py
xlfly/copyover.py
xlfly/create_shortcut.py
xlfly/debug.py
xlfly/icon.ico
xlfly/pop_template.py
xlfly/python.png
xlfly/scripts.py
xlfly-0.9.0.dist-info/entry_points.txt
xlfly-0.9.0.dist-info/METADATA
xlfly-0.9.0.dist-info/WHEEL
xlfly-0.9.0.dist-info/RECORD
