Metadata-Version: 2.1
Name: xlfly
Version: 0.9.0
Summary: 
Author: Your Name
Author-email: you@example.com
Requires-Python: >=3.9
Classifier: Programming Language :: Python :: 3
Classifier: Programming Language :: Python :: 3.9
Classifier: Programming Language :: Python :: 3.10
Classifier: Programming Language :: Python :: 3.11
Classifier: Programming Language :: Python :: 3.12
Requires-Dist: pandas (>=1.5.2)
Requires-Dist: pillow (>=9.4.0)
Requires-Dist: pywin32 (>=300)
Requires-Dist: setuptools (>=70.1.0)
Requires-Dist: xlwings (>=0.28.0)
